api_explorer_server/__init__.py
api_explorer_server/server.py
api_explorer_mcp-0.1.0.dist-info/METADATA
api_explorer_mcp-0.1.0.dist-info/WHEEL
api_explorer_mcp-0.1.0.dist-info/entry_points.txt
api_explorer_mcp-0.1.0.dist-info/RECORD
