Metadata-Version: 2.4
Name: api-explorer-mcp
Version: 0.1.0
Summary: A Model Context Protocol server for efficient OpenAPI/Swagger specification exploration and API testing
Project-URL: Homepage, https://github.com/your-username/api-explorer-mcp
Project-URL: Repository, https://github.com/your-username/api-explorer-mcp
Project-URL: Documentation, https://github.com/your-username/api-explorer-mcp#readme
Project-URL: Bug Tracker, https://github.com/your-username/api-explorer-mcp/issues
Author: Foad Kesheh
License: MIT
Keywords: api,automation,exploration,llm,mcp,openapi,swagger,testing,web
Classifier: Development Status :: 3 - Alpha
Classifier: Intended Audience :: Developers
Classifier: License :: OSI Approved :: MIT License
Classifier: Programming Language :: Python :: 3
Classifier: Programming Language :: Python :: 3.10
Classifier: Programming Language :: Python :: 3.11
Classifier: Programming Language :: Python :: 3.12
Classifier: Topic :: Internet :: WWW/HTTP :: HTTP Servers
Classifier: Topic :: Software Development :: Libraries :: Python Modules
Classifier: Topic :: Software Development :: Testing
Requires-Python: >=3.10
Requires-Dist: anyio>=4.5
Requires-Dist: click>=8.1.0
Requires-Dist: httpx>=0.27
Requires-Dist: mcp
Requires-Dist: pyyaml>=6.0
Requires-Dist: starlette
Requires-Dist: uvicorn
